[
   {
      "set_number" : "SHSP-EN000",
      "rarity" : "Super Rare",
      "name" : "Ghostrick Ghoul"
   },
   {
      "set_number" : "SHSP-EN001",
      "rarity" : "Super Rare",
      "name" : "Labradorite Dragon"
   },
   {
      "rarity" : "Common",
      "name" : "Chow Chow Chan",
      "set_number" : "SHSP-EN002"
   },
   {
      "set_number" : "SHSP-EN003",
      "rarity" : "Common",
      "name" : "Malicevorous Spoon"
   },
   {
      "rarity" : "Common",
      "name" : "Malicevorous Fork",
      "set_number" : "SHSP-EN004"
   },
   {
      "rarity" : "Common",
      "name" : "Malicevorous Knife",
      "set_number" : "SHSP-EN005"
   },
   {
      "set_number" : "SHSP-EN006",
      "name" : "Battlin' Boxer Rib Gardna",
      "rarity" : "Common"
   },
   {
      "name" : "Battlin' Boxer Rabbit Puncher",
      "rarity" : "Common",
      "set_number" : "SHSP-EN007"
   },
   {
      "set_number" : "SHSP-EN008",
      "rarity" : "Common",
      "name" : "Secret Sect Druid Wid"
   },
   {
      "set_number" : "SHSP-EN009",
      "rarity" : "Common",
      "name" : "Secret Sect Druid Dru"
   },
   {
      "set_number" : "SHSP-EN010",
      "name" : "Mythic Tree Dragon",
      "rarity" : "Common"
   },
   {
      "set_number" : "SHSP-EN011",
      "name" : "Mythic Water Dragon",
      "rarity" : "Common"
   },
   {
      "set_number" : "SHSP-EN012",
      "rarity" : "Common",
      "name" : "Armed Protector Dragon"
   },
   {
      "set_number" : "SHSP-EN013",
      "rarity" : "Common",
      "name" : "Soul Drain Dragon"
   },
   {
      "rarity" : "Common",
      "name" : "Baby Raccoon Ponpoko",
      "set_number" : "SHSP-EN014"
   },
   {
      "name" : "Baby Raccoon Tantan",
      "rarity" : "Common",
      "set_number" : "SHSP-EN015"
   },
   {
      "name" : "Ghostrick Lantern",
      "rarity" : "Super Rare",
      "set_number" : "SHSP-EN016"
   },
   {
      "set_number" : "SHSP-EN017",
      "name" : "Ghostrick Specter",
      "rarity" : "Common"
   },
   {
      "set_number" : "SHSP-EN018",
      "name" : "Ghostrick Witch",
      "rarity" : "Common"
   },
   {
      "name" : "Ghostrick Yuki-onna",
      "rarity" : "Common",
      "set_number" : "SHSP-EN019"
   },
   {
      "rarity" : "Common",
      "name" : "Ghostrick Jiangshi",
      "set_number" : "SHSP-EN020"
   },
   {
      "rarity" : "Common",
      "name" : "Ghostrick Stein",
      "set_number" : "SHSP-EN021"
   },
   {
      "set_number" : "SHSP-EN022",
      "name" : "Bujin Mikazuchi",
      "rarity" : "Ultra Rare"
   },
   {
      "set_number" : "SHSP-EN023",
      "name" : "Bujingi Crow",
      "rarity" : "Rare"
   },
   {
      "rarity" : "Common",
      "name" : "Bujingi Ibis",
      "set_number" : "SHSP-EN024"
   },
   {
      "set_number" : "SHSP-EN025",
      "name" : "Bujingi Boar",
      "rarity" : "Common"
   },
   {
      "name" : "Bujingi Centipede",
      "rarity" : "Common",
      "set_number" : "SHSP-EN026"
   },
   {
      "set_number" : "SHSP-EN027",
      "name" : "Mecha Phantom Beast Sabre Hawk",
      "rarity" : "Common"
   },
   {
      "rarity" : "Rare",
      "name" : "Mecha Phantom Beast Kalgriffin",
      "set_number" : "SHSP-EN028"
   },
   {
      "set_number" : "SHSP-EN029",
      "name" : "Vampire Sorcerer",
      "rarity" : "Ultra Rare"
   },
   {
      "rarity" : "Secret Rare",
      "name" : "Shadow Vampire",
      "set_number" : "SHSP-EN030"
   },
   {
      "set_number" : "SHSP-EN031",
      "name" : "Vampire Grace",
      "rarity" : "Common"
   },
   {
      "rarity" : "Common",
      "name" : "Pumprincess the Princess of Ghosts",
      "set_number" : "SHSP-EN032"
   },
   {
      "name" : "Yellow-Bellied Oni",
      "rarity" : "Common",
      "set_number" : "SHSP-EN033"
   },
   {
      "set_number" : "SHSP-EN034",
      "name" : "Vampire Hunter",
      "rarity" : "Super Rare"
   },
   {
      "set_number" : "SHSP-EN035",
      "name" : "Aratama",
      "rarity" : "Rare"
   },
   {
      "name" : "Rasetsu",
      "rarity" : "Common",
      "set_number" : "SHSP-EN036"
   },
   {
      "rarity" : "Common",
      "name" : "Skelesaurus",
      "set_number" : "SHSP-EN037"
   },
   {
      "name" : "Knight Day Grepher",
      "rarity" : "Common",
      "set_number" : "SHSP-EN038"
   },
   {
      "set_number" : "SHSP-EN039",
      "name" : "Genomix Fighter‎",
      "rarity" : "Ultra Rare"
   },
   {
      "set_number" : "SHSP-EN040",
      "name" : "Mariña, Princess of Sunflowers",
      "rarity" : "Super Rare"
   },
   {
      "name" : "Granmarg the Mega Monarch",
      "rarity" : "Secret Rare",
      "set_number" : "SHSP-EN041"
   },
   {
      "set_number" : "SHSP-EN042",
      "rarity" : "Rare",
      "name" : "Swarm of Crows"
   },
   {
      "name" : "Terrene Toothed Tsuchinoko‎",
      "rarity" : "Common",
      "set_number" : "SHSP-EN043"
   },
   {
      "name" : "Risebell the Star Psycher",
      "rarity" : "Short Print",
      "set_number" : "SHSP-EN044"
   },
   {
      "set_number" : "SHSP-EN045",
      "name" : "Blue Duston",
      "rarity" : "Short Print"
   },
   {
      "set_number" : "SHSP-EN046",
      "name" : "Number C96: Dark Storm",
      "rarity" : "Super Rare/Ultimate Rare"
   },
   {
      "set_number" : "SHSP-EN047",
      "rarity" : "Rare",
      "name" : "Number 65: Djinn Buster"
   },
   {
      "rarity" : "Rare",
      "name" : "Number C65: King Overfiend",
      "set_number" : "SHSP-EN048"
   },
   {
      "name" : "Battlin' Boxer Cheat Commissioner",
      "rarity" : "Rare",
      "set_number" : "SHSP-EN049"
   },
   {
      "set_number" : "SHSP-EN050",
      "name" : "Number 46: Dragluon",
      "rarity" : "Super Rare/Ultimate Rare"
   },
   {
      "set_number" : "SHSP-EN051",
      "name" : "Number 64: Ronin Raccoon Sandayu",
      "rarity" : "Rare"
   },
   {
      "rarity" : "Ultra Rare/Ultimate Rare",
      "name" : "Ghostrick Alucard",
      "set_number" : "SHSP-EN052"
   },
   {
      "set_number" : "SHSP-EN053",
      "rarity" : "Ultra Rare/Ultimate Rare",
      "name" : "Bujintei Kagutsuchi"
   },
   {
      "name" : "Crimson Knight Vampire Bram",
      "rarity" : "Ultra Rare",
      "set_number" : "SHSP-EN054"
   },
   {
      "name" : "Meliae of the Trees",
      "rarity" : "Secret Rare",
      "set_number" : "SHSP-EN055"
   },
   {
      "set_number" : "SHSP-EN056",
      "name" : "Divine Dragon Knight Felgrand",
      "rarity" : "Ultimate Rare/Secret Rare/Ghost Rare"
   },
   {
      "name" : "Puralis, the Purple Pyrotile",
      "rarity" : "Rare",
      "set_number" : "SHSP-EN057"
   },
   {
      "name" : "Giganticastle",
      "rarity" : "Rare",
      "set_number" : "SHSP-EN058"
   },
   {
      "rarity" : "Common",
      "name" : "Gagagatag",
      "set_number" : "SHSP-EN059"
   },
   {
      "set_number" : "SHSP-EN060",
      "name" : "Battlin' Boxing Spirits",
      "rarity" : "Super Rare"
   },
   {
      "name" : "Dragon Shield",
      "rarity" : "Common",
      "set_number" : "SHSP-EN061"
   },
   {
      "rarity" : "Common",
      "name" : "Ghostrick Mansion",
      "set_number" : "SHSP-EN062"
   },
   {
      "set_number" : "SHSP-EN063",
      "rarity" : "Rare",
      "name" : "Bujin Regalia - The Mirror"
   },
   {
      "set_number" : "SHSP-EN064",
      "rarity" : "Common",
      "name" : "Vampire Kingdom"
   },
   {
      "rarity" : "Secret Rare",
      "name" : "Pot of Dichotomy",
      "set_number" : "SHSP-EN065"
   },
   {
      "set_number" : "SHSP-EN066",
      "rarity" : "Rare",
      "name" : "Swords at Dawn"
   },
   {
      "set_number" : "SHSP-EN067",
      "name" : "Return of the Monarchs",
      "rarity" : "Ultra Rare"
   },
   {
      "name" : "Sacred Serpent's Wake",
      "rarity" : "Common",
      "set_number" : "SHSP-EN068"
   },
   {
      "set_number" : "SHSP-EN069",
      "rarity" : "Short Print",
      "name" : "Magicalized Duston Mop"
   },
   {
      "name" : "Burst Rebirth",
      "rarity" : "Rare",
      "set_number" : "SHSP-EN070"
   },
   {
      "name" : "Numbers Overlay Boost",
      "rarity" : "Common",
      "set_number" : "SHSP-EN071"
   },
   {
      "rarity" : "Common",
      "name" : "Intrigue Shield",
      "set_number" : "SHSP-EN072"
   },
   {
      "set_number" : "SHSP-EN073",
      "rarity" : "Common",
      "name" : "Ghostrick Vanish"
   },
   {
      "set_number" : "SHSP-EN074",
      "rarity" : "Common",
      "name" : "Ghostrick Scare"
   },
   {
      "set_number" : "SHSP-EN075",
      "rarity" : "Super Rare",
      "name" : "Vampire Takeover"
   },
   {
      "set_number" : "SHSP-EN076",
      "name" : "Mistake",
      "rarity" : "Secret Rare"
   },
   {
      "rarity" : "Common",
      "name" : "Chain Ignition",
      "set_number" : "SHSP-EN077"
   },
   {
      "name" : "Grisaille Prison",
      "rarity" : "Rare",
      "set_number" : "SHSP-EN078"
   },
   {
      "set_number" : "SHSP-EN079",
      "name" : "Survival of the Fittest‎",
      "rarity" : "Common"
   },
   {
      "set_number" : "SHSP-EN080",
      "rarity" : "Short Print",
      "name" : "BIG Win!?"
   },
   {
      "rarity" : "Rare",
      "name" : "Bujingi Raven",
      "set_number" : "SHSP-EN081"
   },
   {
      "name" : "Vampire Duke",
      "rarity" : "Rare",
      "set_number" : "SHSP-EN082"
   },
   {
      "name" : "Archfiend Giant",
      "rarity" : "Rare",
      "set_number" : "SHSP-EN083"
   },
   {
      "set_number" : "SHSP-EN084",
      "rarity" : "Secret Rare",
      "name" : "Lady of the Lake"
   },
   {
      "set_number" : "SHSP-EN085",
      "name" : "Noble Knight Borz",
      "rarity" : "Super Rare"
   },
   {
      "set_number" : "SHSP-EN086",
      "name" : "Ignoble Knight of High Laundsallyn",
      "rarity" : "Secret Rare"
   },
   {
      "rarity" : "Ultra Rare",
      "name" : "Sacred Noble Knight of King Artorigus",
      "set_number" : "SHSP-EN087"
   },
   {
      "set_number" : "SHSP-EN088",
      "rarity" : "Super Rare",
      "name" : "Noble Arms - Excaliburn"
   },
   {
      "set_number" : "SHSP-EN089",
      "rarity" : "Ultra Rare",
      "name" : "Sinister Yorishiro"
   },
   {
      "rarity" : "Ultra Rare",
      "name" : "Celestial Wolf Lord, Blue Sirius",
      "set_number" : "SHSP-EN090"
   },
   {
      "set_number" : "SHSP-EN091",
      "rarity" : "Common",
      "name" : "Mira the Star-Bearer"
   },
   {
      "set_number" : "SHSP-EN092",
      "rarity" : "Super Rare",
      "name" : "Dragard"
   },
   {
      "set_number" : "SHSP-EN093",
      "rarity" : "Common",
      "name" : "White Dragon Wyverburster"
   },
   {
      "set_number" : "SHSP-EN094",
      "rarity" : "Super Rare",
      "name" : "Kidmodo Dragon"
   },
   {
      "set_number" : "SHSP-EN095",
      "name" : "Secret Sanctuary of the Spellcasters",
      "rarity" : "Rare"
   },
   {
      "set_number" : "SHSP-EN096",
      "name" : "Black Dragon Collapserpent",
      "rarity" : "Common"
   },
   {
      "set_number" : "SHSP-EN097",
      "name" : "Armored Kappa",
      "rarity" : "Super Rare"
   },
   {
      "rarity" : "Rare",
      "name" : "Oh Tokenbaum!",
      "set_number" : "SHSP-EN098"
   },
   {
      "set_number" : "SHSP-EN099",
      "name" : "Vivid Knight",
      "rarity" : "Rare"
   }
]
